spaceone/__init__.py
spaceone/cost_analysis/__init__.py
spaceone/cost_analysis/conf/__init__.py
spaceone/cost_analysis/conf/global_conf.py
spaceone/cost_analysis/connector/__init__.py
spaceone/cost_analysis/connector/currency_connector.py
spaceone/cost_analysis/connector/datasource_plugin_connector.py
spaceone/cost_analysis/connector/smtp_connector.py
spaceone/cost_analysis/error/__init__.py
spaceone/cost_analysis/error/budget.py
spaceone/cost_analysis/error/cost.py
spaceone/cost_analysis/error/cost_analysis.py
spaceone/cost_analysis/error/data_source.py
spaceone/cost_analysis/error/data_source_rule.py
spaceone/cost_analysis/error/job.py
spaceone/cost_analysis/error/job_task.py
spaceone/cost_analysis/info/__init__.py
spaceone/cost_analysis/info/budget_info.py
spaceone/cost_analysis/info/budget_usage_info.py
spaceone/cost_analysis/info/common_info.py
spaceone/cost_analysis/info/cost_info.py
spaceone/cost_analysis/info/cost_query_set_info.py
spaceone/cost_analysis/info/data_source_info.py
spaceone/cost_analysis/info/data_source_rule_info.py
spaceone/cost_analysis/info/job_info.py
spaceone/cost_analysis/info/job_task_info.py
spaceone/cost_analysis/interface/__init__.py
spaceone/cost_analysis/interface/grpc/__init__.py
spaceone/cost_analysis/interface/grpc/budget.py
spaceone/cost_analysis/interface/grpc/budget_usage.py
spaceone/cost_analysis/interface/grpc/cost.py
spaceone/cost_analysis/interface/grpc/cost_query_set.py
spaceone/cost_analysis/interface/grpc/cost_report.py
spaceone/cost_analysis/interface/grpc/cost_report_config.py
spaceone/cost_analysis/interface/grpc/cost_report_data.py
spaceone/cost_analysis/interface/grpc/data_source.py
spaceone/cost_analysis/interface/grpc/data_source_account.py
spaceone/cost_analysis/interface/grpc/data_source_rule.py
spaceone/cost_analysis/interface/grpc/job.py
spaceone/cost_analysis/interface/grpc/job_task.py
spaceone/cost_analysis/interface/task/__init__.py
spaceone/cost_analysis/interface/task/v1/__init__.py
spaceone_cost_analysis-2.0.108.dist-info/METADATA
spaceone_cost_analysis-2.0.108.dist-info/WHEEL
spaceone_cost_analysis-2.0.108.dist-info/top_level.txt
spaceone_cost_analysis-2.0.108.dist-info/RECORD
