Metadata-Version: 2.1
Name: spaceone-cost-analysis
Version: 2.0.108
Summary: SpaceONE cost analysis service
Home-page: https://www.spaceone.dev/
Author: MEGAZONE SpaceONE Team
Author-email: admin@spaceone.dev
License: Apache License 2.0
Platform: UNKNOWN
Requires-Dist: spaceone-core
Requires-Dist: spaceone-api
Requires-Dist: pandas
Requires-Dist: numpy
